accessiontk/__init__.py
accessiontk/webmap/__init__.py
accessiontk/webmap/__main__.py
accessiontk/webmap/index.html
accessiontk/webmap/mapapp.js
accessiontk/webmap/meta_fix.R
accessiontk-0.1.1.dist-info/entry_points.txt
accessiontk-0.1.1.dist-info/WHEEL
accessiontk-0.1.1.dist-info/METADATA
accessiontk-0.1.1.dist-info/RECORD
