Metadata-Version: 2.1
Name: accessiontk
Version: 0.1.1
Summary: Tools to manage lists of accessions
Author-email: kdm9 <foss@kdmurray.id.au>
Classifier: Framework :: IPython
Classifier: License :: OSI Approved :: BSD License
Classifier: Programming Language :: Python :: 3
Classifier: Topic :: System :: Shells
Requires-Dist: pillow
Requires-Dist: tqdm
Requires-Dist: heif-image-plugin
